sphinx_proofscape/__init__.py
sphinx_proofscape/chart_widget.py
sphinx_proofscape/lang_exts.py
sphinx_proofscape/lexer.py
sphinx_proofscape-0.4.0.dist-info/LICENSE
sphinx_proofscape-0.4.0.dist-info/METADATA
sphinx_proofscape-0.4.0.dist-info/NOTICE
sphinx_proofscape-0.4.0.dist-info/WHEEL
sphinx_proofscape-0.4.0.dist-info/top_level.txt
sphinx_proofscape-0.4.0.dist-info/RECORD
